{
    "folder_id": "2025-10-10_001",
    "caption": "Forza, Eugenio Giani!\n\nC’è da proseguire un grande lavoro per la Toscana, con una coalizione progressista ancora più ampia! In questi anni la Toscana ha messo al centro la cura delle persone, i nidi gratuiti, la buona impresa e il lavoro di qualità. Ha saputo essere coraggiosa approvando leggi che la destra ha ostacolato, da quella sul salario minimo a quella per regolare gli affitti brevi, dai consorzi pubblici industriali a quella per un fine vita dignitoso.\nUna terra di solidarietà e diritti che può continuare ad innovare, avendo cura di non lasciare indietro nessuno. \nIn bocca al lupo a tutte le candidate e i candidati del Partito Democratico e forza Eugenio! Siamo con te!",
    "type": "image",
    "text": "i regionali tore",
    "language": "it"
}