{
    "folder_id": "2025-10-01_002",
    "caption": ".",
    "type": "image",
    "text": "Quel che sta succedendo è grave. Ho tenuto i contatti con il senatore del M5S Marco Croatti finché possibile. Apprendo che la Marina militare israeliana sta completando l'abbordaggio dei cittadini che pacificamente erano diretti a Gaza con la Flotilla. E un blocco illegale e una violazione del diritto internazionale che arriva dopo che i nostri governi - al contrario di questi coraggiosi cittadini - si son girati dall'altra parte per due anni di fronte a un genocidio. Nessuno tocchi loro un capello. Chi è a capo del Governo, di fronte al valore di questa iniziativa umanitaria, dovrebbe adoperarsi per garantire la massima incolumità, anziché insultare giorno e notte chi alza la testa contro uno dei più grandi crimini della nostra storia recente.",
    "language": "it"
}