{
    "folder_id": "2026-03-25_001",
    "caption": "Oggi a Roma, in Campidoglio, all’evento “Proteggere chi viaggia – soccorso d’emergenza, responsabilità e diritti”, promosso dall’Autorità di regolazione dei trasporti.\n\nUn momento importante di confronto e riflessione: dietro ogni intervento di emergenza ci sono vite, famiglie, storie. Per questo ho voluto ringraziare tutti gli operatori del soccorso d’emergenza, donne e uomini che ogni giorno mettono al primo posto gli altri con professionalità, coraggio e umanità.\n\nI dati confermano che grazie anche al nuovo Codice della Strada, le vittime degli incidenti sono in calo. Nel 2025 meno morti e meno feriti, anche se c'è ancora molto da fare. Avanti così.",
    "type": "image",
    "text": "latteo Salvini",
    "language": "it"
}