{
    "folder_id": "2025-11-10_002",
    "caption": "Sta emergendo un quadro grave e desolante sulle modalità di gestione dell’Autorità Garante per la Privacy che rende necessario un segnale forte di discontinuità. Io penso che non ci sia alternativa alle dimissioni dell’intero consiglio. \n\nLe inchieste giornalistiche di Report hanno rivelato un sistema gestionale opaco, caratterizzato da numerosi conflitti di interesse e da una forte permeabilità alla politica. Senza un azzeramento e una ripartenza sarà impossibile ricostruire la fiducia dei cittadini nell’istituzione che deve tutelarne i diritti e assicurare la necessaria terzietà del collegio, anche rispetto alla politica.",
    "type": "image",
    "text": "la Repubblica Schiein: «Quadro grave, dopo il caso Report si dimetta l'intero consiglio del Garante Privacy»",
    "language": "it"
}