{
    "folder_id": "2026-01-15_001",
    "caption": "Saremo al presidio venerdì 16 gennaio alle 16:00, in Piazza del Campidoglio a Roma, organizzato dal Movimento “Donna, Vita, Libertà” e da Amnesty International per sostenere l’autodeterminazione del popolo iraniano ed esprimere solidarietà ai manifestanti contro il regime di Teheran, che sta massacrando chi lotta per la propria libertà.",
    "type": "image",
    "text": "AL FIANCO DEL POPOLO IRANIANO Il Partito Democratico aderisce: - alla manifestazione di solidarietà ‘ i contro la repressione del regime Va Piazza del Campidoglio, Roma . H Venerdi 16 gennaio, ore 16:00 Pa cani) femocrarità",
    "language": "it"
}